.DS_Store
unitids/__init__.py
unitids/unitids.py
unitids-1.0.5.dist-info/LICENSE
unitids-1.0.5.dist-info/METADATA
unitids-1.0.5.dist-info/WHEEL
unitids-1.0.5.dist-info/top_level.txt
unitids-1.0.5.dist-info/RECORD
